mootlib/__init__.py
mootlib/embeddings/__init__.py
mootlib/embeddings/embedding_utils.py
mootlib/embeddings/question_matcher.py
mootlib/embeddings/remote_cache.py
mootlib/embeddings/visualize_embeddings.py
mootlib/pipeline/__init__.py
mootlib/scrapers/__init__.py
mootlib/scrapers/aggregate.py
mootlib/scrapers/common_markets.py
mootlib/scrapers/gjopen.py
mootlib/scrapers/manifold_markets.py
mootlib/scrapers/metaculus.py
mootlib/scrapers/polymarket_gamma.py
mootlib/scrapers/predictit.py
mootlib/utils/__init__.py
mootlib/utils/encryption.py
mootlib-0.3.0.dist-info/METADATA
mootlib-0.3.0.dist-info/WHEEL
mootlib-0.3.0.dist-info/licenses/LICENSE
mootlib-0.3.0.dist-info/RECORD
