Metadata-Version: 2.4
Name: mootlib
Version: 0.3.0
Summary: A library for scraping and analyzing forecasting markets
Project-URL: Homepage, https://github.com/vigji/mootlib
Project-URL: Repository, https://github.com/vigji/mootlib.git
Project-URL: Documentation, https://github.com/vigji/mootlib
Project-URL: Bug Tracker, https://github.com/vigji/mootlib/issues
Author-email: Luigi Petrucco <luigi.petrucco@gmail.com>
License: MIT
License-File: LICENSE
Keywords: forecasting,markets,prediction,scraping
Classifier: Development Status :: 3 - Alpha
Classifier: Intended Audience :: Science/Research
Classifier: License :: OSI Approved :: MIT License
Classifier: Programming Language :: Python :: 3
Classifier: Programming Language :: Python :: 3.11
Classifier: Topic :: Scientific/Engineering :: Artificial Intelligence
Requires-Python: >=3.11
Requires-Dist: aiohttp>=3.9.3
Requires-Dist: beautifulsoup4>=4.12.0
Requires-Dist: forecasting-tools>=0.1.0
Requires-Dist: openai>=1.3.0
Requires-Dist: pandas<3.0.0,>=2.0.0
Requires-Dist: python-dotenv>=1.0.1
Requires-Dist: requests>=2.31.0
Requires-Dist: scikit-learn>=1.3.2
Requires-Dist: tqdm>=4.65.0
Provides-Extra: dev
Requires-Dist: mypy>=1.3.0; extra == 'dev'
Requires-Dist: pre-commit>=3.5.0; extra == 'dev'
Requires-Dist: pytest-asyncio>=0.21.0; extra == 'dev'
Requires-Dist: pytest-cov>=4.1.0; extra == 'dev'
Requires-Dist: pytest>=7.4.0; extra == 'dev'
Requires-Dist: ruff>=0.2.1; extra == 'dev'
